mcp_yuye_data_analyzer/__init__.py
mcp_yuye_data_analyzer/__main__.py
mcp_yuye_data_analyzer/cli.py
mcp_yuye_data_analyzer/core.py
mcp_yuye_data_analyzer-0.6.dist-info/METADATA
mcp_yuye_data_analyzer-0.6.dist-info/WHEEL
mcp_yuye_data_analyzer-0.6.dist-info/entry_points.txt
mcp_yuye_data_analyzer-0.6.dist-info/top_level.txt
mcp_yuye_data_analyzer-0.6.dist-info/RECORD
